pippkgapi/__init__.py
pippkgapi/packages.py
pippkgapi/releases.py
pippkg_api-0.0.2.dist-info/METADATA
pippkg_api-0.0.2.dist-info/WHEEL
pippkg_api-0.0.2.dist-info/top_level.txt
pippkg_api-0.0.2.dist-info/zip-safe
pippkg_api-0.0.2.dist-info/RECORD
